<?xml version="1.0" encoding="UTF-8"?>
<objects serializationModel="Studio.02.02.00">
	<object class="EncodingSetting" id="{de404899-b3d6-4085-b474-11ed4e2d3106}">
		<property name="encodingFormat">
			<value>3</value>
		</property>
		<property name="quality">
			<value>37</value>
		</property>
		<relationship name="platform">
			<destination>{beda8108-7c9b-4c14-ae67-bed01270c3fa}</destination>
		</relationship>
		<relationship name="encodable">
			<destination>{beda8108-7c9b-4c14-ae67-bed01270c3fa}</destination>
		</relationship>
	</object>
</objects>
