{"inkVersion":20,"root":[[{"->":"Day1"},["done",{"#f":5,"#n":"g-0"}],null],"done",{"Day1":["^I'd like to trade.","\n","end",{"GoodTrade":["^Thanks!","\n","end",{"#f":1}],"BadTrade":["^Well, that's okay too...","\n","end",{"#f":1}],"#f":1}],"Day2":["^I'd like to trade.","\n","end",{"GoodTrade":["^Thanks!","\n","end",{"#f":1}],"BadTrade":["^Well, that's okay too...","\n","end",{"#f":1}],"#f":1}],"Day3":["^I'd like to trade.","\n","end",{"GoodTrade":["^Thanks!","\n","end",{"#f":1}],"BadTrade":["^Well, that's okay too...","\n","end",{"#f":1}],"#f":1}],"Day4":["^I'd like to trade.","\n","end",{"GoodTrade":["^Thanks!","\n","end",{"#f":1}],"BadTrade":["^Well, that's okay too...","\n","end",{"#f":1}],"#f":1}],"Day5":["^I'd like to trade.","\n","end",{"GoodTrade":["^Thanks!","\n","end",{"#f":1}],"BadTrade":["^Well, that's okay too...","\n","end",{"#f":1}],"#f":1}],"Day6":["^I'd like to trade.","\n","end",{"GoodTrade":["^Thanks!","\n","end",{"#f":1}],"BadTrade":["^Well, that's okay too...","\n","end",{"#f":1}],"#f":1}],"Day7":["^I'd like to trade.","\n","end",{"GoodTrade":["^Thanks!","\n","end",{"#f":1}],"BadTrade":["^Well, that's okay too...","\n","end",{"#f":1}],"#f":1}],"Day8":["^I'd like to trade.","\n","end",{"GoodTrade":["^Thanks!","\n","end",{"#f":1}],"BadTrade":["^Well, that's okay too...","\n","end",{"#f":1}],"#f":1}],"Day9":["^I'd like to trade.","\n","end",{"GoodTrade":["^Thanks!","\n","end",{"#f":1}],"BadTrade":["^Well, that's okay too...","\n","end",{"#f":1}],"#f":1}],"Day10":["^I'd like to trade.","\n","end",{"GoodTrade":["^Thanks!","\n","end",{"#f":1}],"BadTrade":["^Well, that's okay too...","\n","end",{"#f":1}],"#f":1}],"Day11":["^I'd like to trade.","\n","end",{"GoodTrade":["^Thanks!","\n","end",{"#f":1}],"BadTrade":["^Well, that's okay too...","\n","end",{"#f":1}],"#f":1}],"Day12":["^I'd like to trade.","\n","end",{"GoodTrade":["^Thanks!","\n","end",{"#f":1}],"BadTrade":["^Well, that's okay too...","\n","end",{"#f":1}],"#f":1}],"Day13":["^I'd like to trade.","\n","end",{"GoodTrade":["^Thanks!","\n","end",{"#f":1}],"BadTrade":["^Well, that's okay too...","\n","end",{"#f":1}],"#f":1}],"Day14":["^I'd like to trade.","\n","end",{"GoodTrade":["^Thanks!","\n","end",{"#f":1}],"BadTrade":["^Well, that's okay too...","\n","end",{"#f":1}],"#f":1}],"Day15":["^I'd like to trade.","\n","end",{"GoodTrade":["^Thanks!","\n","end",{"#f":1}],"BadTrade":["^Well, that's okay too...","\n","end",{"#f":1}],"#f":1}],"Day16":["^I'd like to trade.","\n","end",{"GoodTrade":["^Thanks!","\n","end",{"#f":1}],"BadTrade":["^Well, that's okay too...","\n","end",{"#f":1}],"#f":1}],"Day17":["^I'd like to trade.","\n","end",{"GoodTrade":["^Thanks!","\n","end",{"#f":1}],"BadTrade":["^Well, that's okay too...","\n","end",{"#f":1}],"#f":1}],"Day18":["^I'd like to trade.","\n","end",{"GoodTrade":["^Thanks!","\n","end",{"#f":1}],"BadTrade":["^Well, that's okay too...","\n","end",{"#f":1}],"#f":1}],"Day19":["^I'd like to trade.","\n","end",{"GoodTrade":["^Thanks!","\n","end",{"#f":1}],"BadTrade":["^Well, that's okay too...","\n","end",{"#f":1}],"#f":1}],"Day20":["^I'd like to trade.","\n","end",{"GoodTrade":["^Thanks!","\n","end",{"#f":1}],"BadTrade":["^Well, that's okay too...","\n","end",{"#f":1}],"#f":1}],"Day21":["^I'd like to trade.","\n","end",{"GoodTrade":["^Thanks!","\n","end",{"#f":1}],"BadTrade":["^Well, that's okay too...","\n","end",{"#f":1}],"#f":1}],"#f":1}],"listDefs":{}}